{"at":"2025-09-19T21:47:35.221598","root":".","tree":[".","\u251c\u2500\u2500 app/ (166 files)","\u2502   \u251c\u2500\u2500 src/ (6 files)","\u2502   \u2502   \u2514\u2500\u2500 lib/ (3 files)","\u2502   \u2514\u2500\u2500 package.json","\u2514\u2500\u2500 package.json"],"stats":{"total_files":14,"total_directories":51,"fully_parsed":{"shell":1,"javascript":6},"listed_only":{"json":5,"html":1,"css":1},"markdown_files":1},"f":{"app/build.sh":["s",["generate_random_name:0:()::Function to generate random alphanumeric string","validate_name:0:()::Function to validate project name (alphanumeric only)"]],"app/sr/lib/device-controls.js":["j",{"DeviceControls":["6",["constructor:7:()::","init:17:(options = {})::","setupSideButtonListener:38:():handleSideButtonClick:","setupScrollWheelListener:49:()::","setupKeyboardFallback:65:()::","handleSideButtonClick:81:(event)::","handleScrollWheel:90:(data)::","on:104:(eventType, handler)::","off:116:(eventType, handler)::","setSideButtonEnabled:128:(enabled)::","setScrollWheelEnabled:136:(enabled)::","triggerSideButton:143:()::","__init__:7:()::"]]}],"app/sr/lib/flutter-channel.js":["j",{"FlutterChannel":["14",["constructor:15:()::","checkFlutterAvailability:23:()::","setupPluginMessageHandler:34:()::","sendMessage:51:(message)::","sendPluginMessage:93:(messageObj)::","sendTouchEvent:119:(touchData)::","closeWebView:140:()::","onPluginMessage:153:(callback)::","onSideClick:166:(callback)::","__init__:15:()::"]]}],"app/sr/lib/ui-design.js":["j",{"UIDesign":["6",["constructor:7:()::","pxToVw:19:(px)::","getFontSizes:27:()::","getSpacing:41:()::","getButtonSizes:56:()::","createContainer:86:(element, options = {}):getSpacing:","createButton:112:(button, options = {})::","createText:158:(element, options = {})::","createGrid:185:(container, options = {}):getSpacing:","getColors:210:()::","setupViewport:233:()::","transition:250:(fromElement, toElement, type = 'slide', duration = 300):fadeTransition,slideTransition:","slideTransition:269:(fromElement, toElement, duration)::","fadeTransition:293:(fromElement, toElement, duration)::","__init__:7:()::"]]}],"app/sr/main.js":["j",["i:13:(n)::","D:13:(t)::","A:13:(t)::","H:13:(t)::","b:13:(t)::","d:13:(t)::","v:13:(t)::","k:13:(t)::","y:13:(t)::","w:13:(t):D,d:","O:13:(t):H,d:","L:13:(t):D,v:","m:13:(t):b,v:","M:13:(t):A,k:","K:13:(t):H,k:","N:13:(t):A,y:","S:13:(t):b,y:","j:13:(t,e)::","_:13:(t,e)::","W:13:(t,e)::","U:13:(t,e)::","R:13:(t,e)::","T:13:(t)::","I:13:(t)::","J:13:(t):moves:","V:13:(t):exportJson:","Y:13:(t):exportFEN:","z:13:(t,e,i):exportFEN,exportJson,move:","X:13:(t,e=2):calculateAiMove:","sendGameEvent:3896:(event, details = {})::","startAccelerometer:3915:()::","stopAccelerometer:3934:()::","calculateChecksum:3951:(str)::","setCookie:3963:(name, value, days = 365)::","getCookie:3987:(name)::","saveToStorage:4011:async (key, value):setCookie:","loadFromStorage:4055:async (key):getCookie:","playAudio:1171:(base64Data, volume = 0.4)::"],{"q":["13",[]],"to":["2259",[]],"ChessConverter":["18",[]],"ChessGame":["93",["constructor:94:()::","makeMove:173:async (fromRow, fromCol, toRow, toCol)::","getPossibleMoves:253:(row, col)::","updateGameStatus:275:()::","updateCachedState:297:()::","isBotTurn:332:()::","generateBotMove:347:async ():aiMove,autoSave,generateMoveCommentary,generateMoveNotation,playSound,recordGameState,squareToCoords,updateCachedState,updateGameStatus:","executeBotMove:433:async ()::","__init__:94:()::"]],"ChessUI":["1651",["constructor:1652:(game)::","initializeBoard:1679:():handleSquareClick,handleTouchCancel,handleTouchEnd,handleTouchStart:","handleSquareClick:1706:async (event)::","handleTouchStart:1712:(event)::","handleTouchEnd:1721:async (event)::","handleTouchCancel:1748:(event)::","getLogicalCoordinates:1762:(displayRow, displayCol)::","getDisplayCoordinates:1783:(logicalRow, logicalCol)::","flipBoard:1804:(callback)::","updateBoardPerspective:1830:()::","handleBotTurn:1851:async ()::","setInputEnabled:1950:(enabled)::","showBotThinking:1964:(show)::","hideInstructionLabel:2008:()::","handleGameEnd:2018:()::","updateGameStateIndicators:2057:()::","updatePlayerTurnIndicator:2073:(currentPlayer, gameMode)::","updateCapturedPiecesDisplay:2153:()::","createMaterialBalanceBar:2250:(balance, gameMode, humanColor)::","updateMoveHistoryDisplay:2278:()::","checkInitialBotTurn:2309:()::","onNewGameStart:2382:()::","__init__:1652:(game)::"]],"this":["1808",[]]}]},"g":[["loadFromStorage","getCookie"],["ChessGame.generateBotMove","updateCachedState"],["w","D"],["K","k"],["ChessGame.generateBotMove","squareToCoords"],["ChessUI.initializeBoard","handleTouchEnd"],["ChessUI.initializeBoard","ChessUI.handleTouchEnd"],["z","move"],["UIDesign.createContainer","getSpacing"],["saveToStorage","setCookie"],["O","d"],["L","v"],["UIDesign.transition","slideTransition"],["DeviceControls.setupSideButtonListener","handleSideButtonClick"],["V","exportJson"],["L","D"],["X","calculateAiMove"],["ChessGame.generateBotMove","updateGameStatus"],["m","v"],["S","b"],["N","y"],["ChessGame.generateBotMove","generateMoveCommentary"],["UIDesign.transition","UIDesign.fadeTransition"],["ChessUI.initializeBoard","ChessUI.handleTouchStart"],["Y","exportFEN"],["UIDesign.createGrid","UIDesign.getSpacing"],["DeviceControls.setupSideButtonListener","DeviceControls.handleSideButtonClick"],["ChessGame.generateBotMove","playSound"],["ChessGame.generateBotMove","aiMove"],["ChessGame.generateBotMove","recordGameState"],["ChessGame.generateBotMove","generateMoveNotation"],["ChessUI.initializeBoard","ChessUI.handleTouchCancel"],["ChessUI.initializeBoard","handleSquareClick"],["ChessGame.generateBotMove","ChessGame.updateCachedState"],["ChessUI.initializeBoard","handleTouchCancel"],["ChessUI.initializeBoard","handleTouchStart"],["K","H"],["M","k"],["ChessUI.initializeBoard","ChessUI.handleSquareClick"],["UIDesign.createGrid","getSpacing"],["M","A"],["w","d"],["UIDesign.transition","fadeTransition"],["ChessGame.generateBotMove","ChessGame.updateGameStatus"],["ChessGame.generateBotMove","autoSave"],["O","H"],["J","moves"],["z","exportJson"],["UIDesign.createContainer","UIDesign.getSpacing"],["m","b"],["z","exportFEN"],["N","A"],["UIDesign.transition","UIDesign.slideTransition"],["S","y"]],"d":{"PLAN.md":["Chess R1 - Ready for Deployment","Status: \u2705 READY FOR RABBIT R1","Completed Features","Next Steps","Deployment Notes"]},"deps":{},"dir_purposes":{"app/src/lib":"Library code and shared modules","app/src":"Source code root directory"},"staleness":1757731655.330645}